pubpypack_package_test_package_albert_nanda-0.0.2.dist-info/METADATA
pubpypack_package_test_package_albert_nanda-0.0.2.dist-info/WHEEL
pubpypack_package_test_package_albert_nanda-0.0.2.dist-info/top_level.txt
pubpypack_package_test_package_albert_nanda-0.0.2.dist-info/entry_points.txt
pubpypack_package_test_package_albert_nanda-0.0.2.dist-info/RECORD
imppkg/harmonic_mean.pyx
imppkg/__init__.py
imppkg/test.json
imppkg/harmonic_mean.c
imppkg/harmonic_mean.cpython-310-x86_64-linux-gnu.so
imppkg/hello.py
imppkg/harmony.py
