Metadata-Version: 2.1
Name: pubpypack-package-test-package-albert-nanda
Version: 0.0.2
Summary: THis is a test package
Home-page: https://github.com/albertnanda/test
Author: Albert Nanda
Author-email: albert.nanda@gmail.com
Requires-Dist: termcolor (<2,>=1.1.0)
